i2cTransceiver.vhdl
library ieee;
use ieee.std_logic_1164.all;
use ieee.numeric_std.all;
use ieee.std_logic_textio.all;

entity i2cTransceiver is
  port(
    send          : in std_logic;
    r_w           : in std_logic;
    ack           : in std_logic;
    addr          : in std_logic_vector(9 downto 0);
    data          : in std_logic_vector(7 downto 0);
    sda           : out std_logic := '1';
    scl           : out std_logic := '1';
    done          : out std_logic
  );
  constant bit_period : time := 20 us ; -- scl clock ~ 50 Khz max
end entity;

architecture arch of i2cTransceiver is
    constant frame10bitDefault : std_logic_vector(0 to 4) := "11110";
    signal frame10bitA : std_logic_vector(0 to 8);
    signal frame7bitA : std_logic_vector(0 to 8);
    signal frameData : std_logic_vector(0 to 8);
  begin
    frame10bitA <= frame10bitDefault & addr(9 downto 8) & r_w & ack;
    frame7bitA <=  addr(6 downto 0) & r_w & ack;
    frameData <=  data(7 downto 0) & ack;
    process
      begin
        wait until send = '1';
        done <= '0';

        wait for (bit_period);


        sda <= '0'; -- Start bit
        
        wait for (bit_period/2);
        scl <= '0';
        wait for (bit_period/2);
        
        if addr(9 downto 7) /= "000" then
          for i in 0 to 8 loop
            sda <= frame10bitA(i);
            
            wait for (bit_period/2);
            scl <= '1';   
            wait for (bit_period/2);
            scl <= '0';
          end loop;
          
          sda <= '1';
          wait for bit_period;
          sda <= '0';
          wait for bit_period;
        end if;

        for i in 0 to 8 loop
          sda <= frame7bitA(i);
          
          wait for (bit_period/2);
          scl <= '1';   
          wait for (bit_period/2);
          scl <= '0';
        end loop;

        sda <= '1';
        wait for bit_period;
        sda <= '0';
        wait for bit_period;

        for i in 0 to 8 loop
          sda <= frameData(i);
          
          wait for (bit_period/2);
          scl <= '1';   
          wait for (bit_period/2);
          scl <= '0';
        end loop;
      
        sda <= '1'; 
        wait for (bit_period/2);
        sda <= '0';
        wait for (bit_period/2);
        scl <= '1';
        wait for (bit_period/2);
        sda <= '1';

        done <= '1';
        
    end process;

end arch;

i2c_tb.vhdl
library ieee;
use ieee.std_logic_1164.all;
use ieee.numeric_std.all;
use ieee.std_logic_textio.all;

library std;
use std.textio.all;

entity i2c_tb is
  constant bit_period : time := 20 us ; -- scl clock ~ 50 Khz max
end entity;

architecture arch of i2c_tb is
  component i2cTransceiver is
    port(
      send          : in std_logic;
      r_w           : in std_logic;
      ack           : in std_logic;
      addr          : in std_logic_vector(9 downto 0);
      data          : in std_logic_vector(7 downto 0);
      sda           : out std_logic;
      scl           : out std_logic;
      done          : out std_logic
    );
  end component;
  signal send       : std_logic;
  signal r_w        : std_logic;
  signal ack        : std_logic;
  signal addr       : std_logic_vector(9 downto 0);
  signal data       : std_logic_vector(7 downto 0);
  signal sda        : std_logic := '1';
  signal scl        : std_logic := '1';
  signal done       : std_logic;

  type dataRecord is record
    address : std_logic_vector(9 downto 0);
    r_w : std_logic;
    ack : std_logic;
    data : std_logic_vector(7 downto 0);
  end record;

  type dataArray is array (natural range <>) of dataRecord;
  constant records : dataArray := (
                            (address => "0001010101", r_w => '0', ack => '1', data => "10101010"),
                            (address => "1100111101", r_w => '1', ack => '1', data => "10101101"),
                            (address => "0010111101", r_w => '0', ack => '1', data => "00011001")
                            );

  begin
    
    UUT : i2cTransceiver port map(send,r_w,ack,addr,data,sda,scl,done);

    process
    procedure send_code( sc : dataRecord ) is
    begin
      addr <= sc.address;
      r_w <= sc.r_w;
      ack <= sc.ack;
      data <= sc.data;
      send <= '1';
      wait for bit_period;
      send <= '0';
      wait until done = '1';
      wait for bit_period*5;
    end procedure send_code;

    begin
        for i in records'range loop
            send_code(records(i));
        end loop;
        wait;
    end process;

end arch;

i2c_tb.vcd
$date
  Sun Jun 14 02:09:13 2020
$end
$version
  GHDL v0
$end
$timescale
  1 fs
$end
$scope module standard $end
$upscope $end
$scope module std_logic_1164 $end
$upscope $end
$scope module numeric_std $end
$upscope $end
$scope module textio $end
$upscope $end
$scope module std_logic_textio $end
$upscope $end
$scope module i2c_tb $end
$var reg 1 ! send $end
$var reg 1 " r_w $end
$var reg 1 # ack $end
$var reg 10 $ addr[9:0] $end
$var reg 8 % data[7:0] $end
$var reg 1 & sda $end
$var reg 1 ' scl $end
$var reg 1 ( done $end
$scope module uut $end
$var reg 1 ) send $end
$var reg 1 * r_w $end
$var reg 1 + ack $end
$var reg 10 , addr[9:0] $end
$var reg 8 - data[7:0] $end
$var reg 1 . sda $end
$var reg 1 / scl $end
$var reg 1 0 done $end
$var reg 9 1 frame10bita[0:8] $end
$var reg 9 2 frame7bita[0:8] $end
$var reg 9 3 framedata[0:8] $end
$upscope $end
$upscope $end
$enddefinitions $end
#0
1!
0"
1#
b0001010101 $
b10101010 %
1&
1'
0(
1)
0*
1+
b0001010101 ,
b10101010 -
1.
1/
00
b111100001 1
b101010101 2
b101010101 3
#20000000000
0!
0&
0)
0.
#30000000000
0'
0/
#40000000000
1&
1.
#50000000000
1'
1/
#60000000000
0&
0'
0.
0/
#70000000000
1'
1/
#80000000000
1&
0'
1.
0/
#90000000000
1'
1/
#100000000000
0&
0'
0.
0/
#110000000000
1'
1/
#120000000000
1&
0'
1.
0/
#130000000000
1'
1/
#140000000000
0&
0'
0.
0/
#150000000000
1'
1/
#160000000000
1&
0'
1.
0/
#170000000000
1'
1/
#180000000000
0&
0'
0.
0/
#190000000000
1'
1/
#200000000000
1&
0'
1.
0/
#210000000000
1'
1/
#220000000000
0'
0/
#240000000000
0&
0.
#260000000000
1&
1.
#270000000000
1'
1/
#280000000000
0&
0'
0.
0/
#290000000000
1'
1/
#300000000000
1&
0'
1.
0/
#310000000000
1'
1/
#320000000000
0&
0'
0.
0/
#330000000000
1'
1/
#340000000000
1&
0'
1.
0/
#350000000000
1'
1/
#360000000000
0&
0'
0.
0/
#370000000000
1'
1/
#380000000000
1&
0'
1.
0/
#390000000000
1'
1/
#400000000000
0&
0'
0.
0/
#410000000000
1'
1/
#420000000000
1&
0'
1.
0/
#430000000000
1'
1/
#440000000000
0'
0/
#450000000000
0&
0.
#460000000000
1'
1/
#470000000000
1&
1(
1.
10
#570000000000
1!
1"
b1100111101 $
b10101101 %
0(
1)
1*
b1100111101 ,
b10101101 -
00
b111101111 1
b011110111 2
b101011011 3
#590000000000
0!
0&
0)
0.
#600000000000
0'
0/
#610000000000
1&
1.
#620000000000
1'
1/
#630000000000
0'
0/
#640000000000
1'
1/
#650000000000
0'
0/
#660000000000
1'
1/
#670000000000
0'
0/
#680000000000
1'
1/
#690000000000
0&
0'
0.
0/
#700000000000
1'
1/
#710000000000
1&
0'
1.
0/
#720000000000
1'
1/
#730000000000
0'
0/
#740000000000
1'
1/
#750000000000
0'
0/
#760000000000
1'
1/
#770000000000
0'
0/
#780000000000
1'
1/
#790000000000
0'
0/
#810000000000
0&
0.
#830000000000
#840000000000
1'
1/
#850000000000
1&
0'
1.
0/
#860000000000
1'
1/
#870000000000
0'
0/
#880000000000
1'
1/
#890000000000
0'
0/
#900000000000
1'
1/
#910000000000
0'
0/
#920000000000
1'
1/
#930000000000
0&
0'
0.
0/
#940000000000
1'
1/
#950000000000
1&
0'
1.
0/
#960000000000
1'
1/
#970000000000
0'
0/
#980000000000
1'
1/
#990000000000
0'
0/
#1000000000000
1'
1/
#1010000000000
0'
0/
#1030000000000
0&
0.
#1050000000000
1&
1.
#1060000000000
1'
1/
#1070000000000
0&
0'
0.
0/
#1080000000000
1'
1/
#1090000000000
1&
0'
1.
0/
#1100000000000
1'
1/
#1110000000000
0&
0'
0.
0/
#1120000000000
1'
1/
#1130000000000
1&
0'
1.
0/
#1140000000000
1'
1/
#1150000000000
0'
0/
#1160000000000
1'
1/
#1170000000000
0&
0'
0.
0/
#1180000000000
1'
1/
#1190000000000
1&
0'
1.
0/
#1200000000000
1'
1/
#1210000000000
0'
0/
#1220000000000
1'
1/
#1230000000000
0'
0/
#1240000000000
0&
0.
#1250000000000
1'
1/
#1260000000000
1&
1(
1.
10
#1360000000000
1!
0"
b0010111101 $
b00011001 %
0(
1)
0*
b0010111101 ,
b00011001 -
00
b111100001 1
b011110101 2
b000110011 3
#1380000000000
0!
0&
0)
0.
#1390000000000
0'
0/
#1400000000000
1&
1.
#1410000000000
1'
1/
#1420000000000
0'
0/
#1430000000000
1'
1/
#1440000000000
0'
0/
#1450000000000
1'
1/
#1460000000000
0'
0/
#1470000000000
1'
1/
#1480000000000
0&
0'
0.
0/
#1490000000000
1'
1/
#1500000000000
0'
0/
#1510000000000
1'
1/
#1520000000000
0'
0/
#1530000000000
1'
1/
#1540000000000
0'
0/
#1550000000000
1'
1/
#1560000000000
1&
0'
1.
0/
#1570000000000
1'
1/
#1580000000000
0'
0/
#1600000000000
0&
0.
#1620000000000
#1630000000000
1'
1/
#1640000000000
1&
0'
1.
0/
#1650000000000
1'
1/
#1660000000000
0'
0/
#1670000000000
1'
1/
#1680000000000
0'
0/
#1690000000000
1'
1/
#1700000000000
0'
0/
#1710000000000
1'
1/
#1720000000000
0&
0'
0.
0/
#1730000000000
1'
1/
#1740000000000
1&
0'
1.
0/
#1750000000000
1'
1/
#1760000000000
0&
0'
0.
0/
#1770000000000
1'
1/
#1780000000000
1&
0'
1.
0/
#1790000000000
1'
1/
#1800000000000
0'
0/
#1820000000000
0&
0.
#1840000000000
#1850000000000
1'
1/
#1860000000000
0'
0/
#1870000000000
1'
1/
#1880000000000
0'
0/
#1890000000000
1'
1/
#1900000000000
1&
0'
1.
0/
#1910000000000
1'
1/
#1920000000000
0'
0/
#1930000000000
1'
1/
#1940000000000
0&
0'
0.
0/
#1950000000000
1'
1/
#1960000000000
0'
0/
#1970000000000
1'
1/
#1980000000000
1&
0'
1.
0/
#1990000000000
1'
1/
#2000000000000
0'
0/
#2010000000000
1'
1/
#2020000000000
0'
0/
#2030000000000
0&
0.
#2040000000000
1'
1/
#2050000000000
1&
1(
1.
10
